kurde/__init__.py
kurde/__main__.py
kurde/core.py
kurde-0.2.0.dist-info/METADATA
kurde-0.2.0.dist-info/WHEEL
kurde-0.2.0.dist-info/entry_points.txt
kurde-0.2.0.dist-info/RECORD
