Metadata-Version: 2.1
Name: kurde
Version: 0.2.0
Summary: Configuration Language
License: MIT
Author: Grzegorz Krasoń
Requires-Python: >=3.8,<4.0
Classifier: License :: OSI Approved :: MIT License
Classifier: Programming Language :: Python :: 3
Classifier: Programming Language :: Python :: 3.8
Classifier: Programming Language :: Python :: 3.9
Classifier: Programming Language :: Python :: 3.10
Classifier: Programming Language :: Python :: 3.11
Requires-Dist: addict (>=2.4.0,<3.0.0)
Requires-Dist: click (>=8.1.7,<9.0.0)
Requires-Dist: orjson (>=3.9.9,<4.0.0)
Requires-Dist: plumbum (>=1.8.2,<2.0.0)
Requires-Dist: pygments (>=2.16.1,<3.0.0)
Requires-Dist: simple-enum (>=0.0.6,<0.0.7)
